{
  "signal": "VENDI",
  "price_usd": 1791.13,
  "price_eur": 1566.94,
  "volume_24h_usd": 10671864667.0,
  "last_update": "2026-07-05 23:30:48 UTC",
  "status": "Attivo",
  "rsi": 58.090127868547995,
  "sma50": 1808.5172533203122,
  "sma200": 2262.8748736328125,
  "atr": 75.21358090867983,
  "risk_level": "ALTO",
  "condition_groups": {
    "buy": [
      {
        "label": "prezzo live sopra SMA200 live",
        "passed": false
      },
      {
        "label": "SMA50 live sopra SMA200 live",
        "passed": false
      },
      {
        "label": "valore RSI live compreso tra 40 e 65",
        "passed": true
      },
      {
        "label": "prezzo live sopra quello di 7 giorni prima",
        "passed": true
      },
      {
        "label": "volume 24h live sopra media 20 giorni",
        "passed": false
      }
    ],
    "sell": [
      {
        "label": "prezzo live sotto SMA50 live",
        "passed": true
      },
      {
        "label": "trailing stop 8%: momentum 7g >= -5% e volume >= media20 +20%",
        "passed": false
      }
    ]
  }
}