{
  "signal": "MANTIENI",
  "price_usd": 1917.45,
  "price_eur": 1680.61,
  "volume_24h_usd": 8811081734.0,
  "last_update": "2026-07-22 13:07:51 UTC",
  "status": "Attivo",
  "rsi": 62.860567290385184,
  "sma50": 1732.3073862304686,
  "sma200": 2166.1369259033204,
  "atr": 63.12197998465411,
  "risk_level": "ALTO",
  "condition_groups": {
    "buy": [
      {
        "label": "prezzo live sopra SMA200 live",
        "passed": false
      },
      {
        "label": "SMA50 live sopra SMA200 live",
        "passed": false
      },
      {
        "label": "valore RSI live compreso tra 40 e 65",
        "passed": true
      },
      {
        "label": "prezzo live sopra quello di 7 giorni prima",
        "passed": true
      },
      {
        "label": "volume 24h live sopra media 20 giorni",
        "passed": false
      }
    ],
    "sell": [
      {
        "label": "prezzo live sotto SMA50 live",
        "passed": false
      },
      {
        "label": "trailing stop 8%: momentum 7g >= -5% e volume >= media20 +20%",
        "passed": false
      }
    ]
  }
}